flake8_no_u_prefixed_strings/__init__.py
flake8_no_u_prefixed_strings-0.2.dist-info/METADATA
flake8_no_u_prefixed_strings-0.2.dist-info/RECORD
flake8_no_u_prefixed_strings-0.2.dist-info/WHEEL
flake8_no_u_prefixed_strings-0.2.dist-info/entry_points.txt
flake8_no_u_prefixed_strings-0.2.dist-info/top_level.txt
