Metadata-Version: 2.1
Name: flake8-no-u-prefixed-strings
Version: 0.2
Summary: Detects and warns about invalid escape sequences.
Home-page: https://github.com/5j9/flake8-no-u-prefixed-strings
Author: 5j9
Author-email: 5j9@users.noreply.github.com
License: GNU General Public License v3 (GPLv3)
Platform: UNKNOWN
Classifier: Framework :: Flake8
Classifier: Environment :: Console
Classifier: Intended Audience :: Developers
Classifier: License :: OSI Approved :: GNU General Public License v3 (GPLv3)
Classifier: Programming Language :: Python
Classifier: Programming Language :: Python :: 2
Classifier: Programming Language :: Python :: 3
Classifier: Topic :: Software Development :: Libraries :: Python Modules
Classifier: Topic :: Software Development :: Quality Assurance
Requires-Dist: flake8 (>3.0.0)
